fmqlreports/__init__.py
fmqlreports/visnNVistAs.py
fmqlreports/visualize.py
fmqlreports/visualizeNext.py
fmqlreports/webReportUtils.py
fmqlreports/basics/__init__.py
fmqlreports/basics/webReportDataTypes.py
fmqlreports/basics/webReportIntro.py
fmqlreports/basics/webReportSubReportDataTypes.py
fmqlreports/cross/webReportInstitutions.py
fmqlreports/directory/buildDirectory.py
fmqlreports/directory/fileDirectory.py
fmqlreports/directory/institutionDirectory.py
fmqlreports/directory/patientDirectory.py
fmqlreports/directory/userDirectory.py
fmqlreports/directory/webReportBuildDirectory.py
fmqlreports/directory/webReportDirectoryUtils.py
fmqlreports/directory/webReportFileDirectory.py
fmqlreports/directory/webReportInstitutions.py
fmqlreports/directory/webReportPatientDirectory.py
fmqlreports/directory/webReportUserDirectory.py
fmqlreports/hl7/hl7Utils.py
fmqlreports/hl7/webReportHL7.py
fmqlreports/hl7/webReportIFCHL7.py
fmqlreports/hl7/webReportSPQHL7.py
fmqlreports/ifc/webReportIFC.py
fmqlreports/ifc/webReportTeleReading.py
fmqlreports/imaging/__init__.py
fmqlreports/imaging/webReportImaging.py
fmqlreports/patient/__init__.py
fmqlreports/patient/flip2.py
fmqlreports/patient/webReportDental.py
fmqlreports/patient/webReportHBPC.py
fmqlreports/patient/webReportHealthFactors.py
fmqlreports/patient/webReportPRFs.py
fmqlreports/patient/webReportPatient.py
fmqlreports/patient/webReportProsthetics.py
fmqlreports/pharmacy/webReportRxCoPayTransactions.py
fmqlreports/schema/__init__.py
fmqlreports/trf/webReportTRF.py
fmqlreports/user/USER_CONSTANTS.py
fmqlreports/user/__init__.py
fmqlreports/user/csvUser.py
fmqlreports/user/userClassifier.py
fmqlreports/user/webReportUser.py
fmqlreports/visit/flip44.py
fmqlreports/visit/webReportEncounters.py
fmqlreports/visit/webReportScheduling.py
fmqlreports-1.2.dist-info/LICENSE.txt
fmqlreports-1.2.dist-info/METADATA
fmqlreports-1.2.dist-info/WHEEL
fmqlreports-1.2.dist-info/top_level.txt
fmqlreports-1.2.dist-info/RECORD
