Metadata-Version: 2.1
Name: fmqlreports
Version: 1.2
Summary: FMQL Reports
Home-page: http://github.com/Caregraf
Author: UNKNOWN
Author-email: UNKNOWN
License: Apache License, Version 2.0
Keywords: VistA,FileMan,CHCS,FMQL,Caregraf
Platform: UNKNOWN
Classifier: Development Status :: 4 - Beta
Classifier: Programming Language :: Python :: 3
Requires-Dist: fmqlutils (>=3.7)
Requires-Dist: python-dateutil
